evfuncs/__about__.py
evfuncs/__init__.py
evfuncs/evfuncs.py
evfuncs-0.3.5.post1.dist-info/LICENSE
evfuncs-0.3.5.post1.dist-info/WHEEL
evfuncs-0.3.5.post1.dist-info/METADATA
evfuncs-0.3.5.post1.dist-info/RECORD
