Metadata-Version: 2.1
Name: evfuncs
Version: 0.3.5.post1
Summary: Functions for working with files created by the EvTAF program and the evsonganaly GUI
Author-email: David Nicholson <nickledave@users.noreply.github.com>
Requires-Python: >=3.8
Classifier: License :: OSI Approved :: BSD License
Classifier: Development Status :: 5 - Production/Stable
Classifier: Programming Language :: Python
Classifier: Programming Language :: Python :: 3
Classifier: Programming Language :: Python :: 3.8
Classifier: Programming Language :: Python :: 3.9
Classifier: Programming Language :: Python :: 3.10
Classifier: Programming Language :: Python :: Implementation :: CPython
Requires-Dist: numpy >=1.18.1
Requires-Dist: scipy >=1.2.0
Requires-Dist: pytest >=6.2.2 ; extra == "test"
Project-URL: Source, https://github.com/NickleDave/evfuncs
Provides-Extra: test
